compatibility_tests/v2.5.0/tests/__init__.py
compatibility_tests/v2.5.0/tests/google/__init__.py
compatibility_tests/v2.5.0/tests/google/protobuf/__init__.py
compatibility_tests/v2.5.0/tests/google/protobuf/internal/__init__.py
google/__init__.py
google/protobuf/__init__.py
google/protobuf/any_pb2.py
google/protobuf/api_pb2.py
google/protobuf/compiler/__init__.py
google/protobuf/compiler/plugin_pb2.py
google/protobuf/descriptor.py
google/protobuf/descriptor_database.py
google/protobuf/descriptor_pb2.py
google/protobuf/descriptor_pool.py
google/protobuf/duration_pb2.py
google/protobuf/empty_pb2.py
google/protobuf/field_mask_pb2.py
google/protobuf/internal/__init__.py
google/protobuf/internal/_parameterized.py
google/protobuf/internal/api_implementation.py
google/protobuf/internal/containers.py
google/protobuf/internal/decoder.py
google/protobuf/internal/encoder.py
google/protobuf/internal/enum_type_wrapper.py
google/protobuf/internal/extension_dict.py
google/protobuf/internal/import_test_package/__init__.py
google/protobuf/internal/message_listener.py
google/protobuf/internal/python_message.py
google/protobuf/internal/testing_refleaks.py
google/protobuf/internal/type_checkers.py
google/protobuf/internal/well_known_types.py
google/protobuf/internal/wire_format.py
google/protobuf/json_format.py
google/protobuf/message.py
google/protobuf/message_factory.py
google/protobuf/proto_builder.py
google/protobuf/pyext/__init__.py
google/protobuf/pyext/cpp_message.py
google/protobuf/reflection.py
google/protobuf/service.py
google/protobuf/service_reflection.py
google/protobuf/source_context_pb2.py
google/protobuf/struct_pb2.py
google/protobuf/symbol_database.py
google/protobuf/text_encoding.py
google/protobuf/text_format.py
google/protobuf/timestamp_pb2.py
google/protobuf/type_pb2.py
google/protobuf/util/__init__.py
google/protobuf/wrappers_pb2.py
__init__.py
deps_proto/deps_pb2.py
pypi__java_manifest/site-packages/__init__.py
pypi__java_manifest/site-packages/java_manifest-1.1.0.dist-info/INSTALLER
pypi__java_manifest/site-packages/java_manifest-1.1.0.dist-info/METADATA
pypi__java_manifest/site-packages/java_manifest-1.1.0.dist-info/WHEEL
unused_deps_py-0.0.6.dist-info/METADATA
unused_deps_py-0.0.6.dist-info/RECORD
unused_deps_py-0.0.6.dist-info/WHEEL
unused_deps_py-0.0.6.dist-info/entry_points.txt
