Metadata-Version: 2.1
Name: unused_deps_py
Version: 0.0.6
Author: Command line tool to detect unused java dependencies with support for rules_jvm_external definitions
Author-email: manuel.naranjo@booking.com
Home-page: https://github.com/bookingcom/buildtools/tree/master/unused_deps_py
License: Apache 2.0
Classifier: License :: OSI Approved :: Apache Software License
Classifier: Intended Audience :: Developers
Classifier: Development Status :: 4 - Beta
Classifier: Environment :: Console
Classifier: Topic :: Software Development :: Build Tools
Requires-Python: >=3
Requires-Dist: java-manifest>=1.1.0
Requires-Dist: six>=1.16.0
